nlcpy/__config__.py
nlcpy/__init__.py
nlcpy/_environment.py
nlcpy/_path.py
nlcpy/_version.py
nlcpy/core/__init__.py
nlcpy/core/broadcast.cpython-36m-x86_64-linux-gnu.so
nlcpy/core/core.cpython-36m-x86_64-linux-gnu.so
nlcpy/core/dtype.cpython-36m-x86_64-linux-gnu.so
nlcpy/core/error.py
nlcpy/core/flags.py
nlcpy/core/indexing.cpython-36m-x86_64-linux-gnu.so
nlcpy/core/internal.cpython-36m-x86_64-linux-gnu.so
nlcpy/core/manipulation.cpython-36m-x86_64-linux-gnu.so
nlcpy/core/math.cpython-36m-x86_64-linux-gnu.so
nlcpy/core/scalar.cpython-36m-x86_64-linux-gnu.so
nlcpy/core/searching.cpython-36m-x86_64-linux-gnu.so
nlcpy/core/sorting.cpython-36m-x86_64-linux-gnu.so
nlcpy/core/vememory.cpython-36m-x86_64-linux-gnu.so
nlcpy/creation/__init__.py
nlcpy/creation/basic.py
nlcpy/creation/from_data.py
nlcpy/creation/matrices.py
nlcpy/creation/ranges.py
nlcpy/datatype/__init__.py
nlcpy/datatype/getlimits.py
nlcpy/error_handler/__init__.py
nlcpy/error_handler/error_handler.py
nlcpy/fft/__init__.py
nlcpy/fft/_fft.cpython-36m-x86_64-linux-gnu.so
nlcpy/fft/fft.py
nlcpy/include/__init__.py
nlcpy/include/array_utility.h
nlcpy/include/fpe_flags.h
nlcpy/include/nlcpy.h
nlcpy/include/ve_array.h
nlcpy/include/ve_dtype.h
nlcpy/include/ve_error.h
nlcpy/include/ve_funclist.h
nlcpy/include/ve_funcnum.h
nlcpy/include/ve_functype.h
nlcpy/include/ve_request.h
nlcpy/include/ve_selector.h
nlcpy/indexing/__init__.py
nlcpy/indexing/generate.py
nlcpy/indexing/indexing.py
nlcpy/indexing/inserting.py
nlcpy/io/__init__.py
nlcpy/io/npz.py
nlcpy/io/text.py
nlcpy/jit/__init__.py
nlcpy/jit/kernel.py
nlcpy/jit/module.py
nlcpy/kernel_register/ve_kernel_register.cpython-36m-x86_64-linux-gnu.so
nlcpy/linalg/__init__.py
nlcpy/linalg/cblas_wrapper.cpython-36m-x86_64-linux-gnu.so
nlcpy/linalg/decomposition.py
nlcpy/linalg/eig.py
nlcpy/linalg/norm.py
nlcpy/linalg/products.py
nlcpy/linalg/solve.py
nlcpy/linalg/util.py
nlcpy/logging/__init__.py
nlcpy/logging/_vp_logging.py
nlcpy/logic/__init__.py
nlcpy-3.0.1.dist-info/LICENSE
nlcpy-3.0.1.dist-info/METADATA
nlcpy-3.0.1.dist-info/WHEEL
nlcpy-3.0.1.dist-info/top_level.txt
nlcpy-3.0.1.dist-info/RECORD
