Metadata-Version: 2.1
Name: nlcpy
Version: 3.0.1
Summary: NLCPy is a package for accelerating performance of Python scripts using NumPy on SX-Aurora TSUBASA.
Home-page: https://github.com/SX-Aurora/nlcpy/
Author: NEC
Author-email: dev-nlcpy@sxarr.jp.nec.com
License: BSD 3-Clause
Project-URL: Bug Tracker, https://github.com/SX-Aurora/nlcpy/issues
Project-URL: Documentation, https://www.hpc.nec/documents/nlcpy/en/index.html
Keywords: nlcpy
Platform: UNKNOWN
Classifier: Development Status :: 5 - Production/Stable
Classifier: License :: OSI Approved :: BSD License
Classifier: Operating System :: POSIX :: Linux
Classifier: Programming Language :: Python :: 3.6
Classifier: Programming Language :: Python :: 3.7
Classifier: Programming Language :: Python :: 3.8
Classifier: Programming Language :: C
Classifier: Programming Language :: Cython
Classifier: Programming Language :: Python :: 3 :: Only
Classifier: Topic :: Scientific/Engineering
Classifier: Topic :: Software Development
Requires-Python: <3.9,>=3.6
License-File: LICENSE
Requires-Dist: numpy (>=1.17)
Requires-Dist: nlcpy-ve1-kernel (==3.0.1)
Requires-Dist: nlcpy-ve3-kernel (==3.0.1)
